{
  "python": "3.12.2",
  "runtime_seconds": 223.52153706550598,
  "args": {
    "outputs_dir": "scalebreak_flyvis/outputs",
    "out_dir": "scalebreak_flyvis/outputs/hex_native_temporal_baseline",
    "seeds": "42",
    "epochs": 10,
    "batch_size": 64,
    "hidden": 96,
    "dropout": 0.2,
    "lr": 0.0005,
    "weight_decay": 0.0001,
    "patience": 4
  },
  "classes": [
    "0.0",
    "120.0",
    "180.0",
    "240.0",
    "300.0",
    "60.0"
  ],
  "stimulus_shape": [
    4320,
    165,
    1,
    721
  ],
  "n_dynamic_trials": 2880
}